example_package/__init__.py
example_package/rivarossa.py
rivarossa-0.0.1.dist-info/LICENSE
rivarossa-0.0.1.dist-info/METADATA
rivarossa-0.0.1.dist-info/WHEEL
rivarossa-0.0.1.dist-info/top_level.txt
rivarossa-0.0.1.dist-info/RECORD
