Metadata-Version: 2.1
Name: rivarossa
Version: 0.0.1
Summary: The best library ever of Rivarossa made by CPC (Copy&Paste Corporation)
Home-page: https://github.com/pypa/sampleproject
Author: 1__ricky-picco__1
Author-email: riccardo.picco@istitutomoro.edu.it
License: UNKNOWN
Project-URL: Bug Tracker, https://github.com/pypa/sampleproject/issues
Platform: UNKNOWN
Classifier: Programming Language :: Python :: 3
Classifier: License :: OSI Approved :: MIT License
Classifier: Operating System :: OS Independent
Requires-Python: >=3.6
License-File: LICENSE
